beetimer/__init__.py
beetimer/beetimer.py
beetimer-0.1.1.dist-info/METADATA
beetimer-0.1.1.dist-info/WHEEL
beetimer-0.1.1.dist-info/entry_points.txt
beetimer-0.1.1.dist-info/RECORD
