Metadata-Version: 2.1
Name: beetimer
Version: 0.1.1
Summary: 
Author: fergus
Author-email: fergusfettes@gmail.com
Requires-Python: >=3.10,<4.0
Classifier: Programming Language :: Python :: 3
Classifier: Programming Language :: Python :: 3.10
Classifier: Programming Language :: Python :: 3.11
Requires-Dist: pyminder (>=1.1.1,<2.0.0)
Requires-Dist: rich (>=13.7.0,<14.0.0)
Requires-Dist: typer (>=0.9.0,<0.10.0)
